xlsxstyler/__init__.py
xlsxstyler/main.py
xlsxstyler-0.1.4.dist-info/WHEEL
xlsxstyler-0.1.4.dist-info/METADATA
xlsxstyler-0.1.4.dist-info/RECORD
